{"type":"CodeCoverage","coverage":[{"source":"package:tokenizer/handlers.dart","script":{"type":"@Script","fixedId":true,"id":"libraries/1/scripts/package%3Atokenizer%2Fhandlers.dart","uri":"package:tokenizer/handlers.dart","_kind":"library"},"hits":[98,1,46,1,47,2,51,1,52,2,56,1,57,7,58,5,60,0,64,1,66,2,67,1,74,1,75,5,76,2,77,4,79,0,83,1,84,7,85,1,87,1,88,2,89,1,94,0,35,1,11,1,12,1,14,2,15,3,17,2,20,2,23,1,24,2,26,2,27,2,29,2,32,2,170,1,112,1,113,7,114,5,116,5,120,1,121,3,122,5,124,0,128,1,129,5,130,2,131,4,133,5,137,1,138,7,139,5,140,2,143,0,147,1,149,1,152,1,153,2,156,3,159,1,160,1,162,2,165,0,166,0,194,0,181,0,186,0,187,0]},{"source":"package:tokenizer/tokenizer.dart","script":{"type":"@Script","fixedId":true,"id":"libraries/1/scripts/package%3Atokenizer%2Ftokenizer.dart","uri":"package:tokenizer/tokenizer.dart","_kind":"library"},"hits":[12,0]},{"source":"package:tokenizer/primitives.dart","script":{"type":"@Script","fixedId":true,"id":"libraries/1/scripts/package%3Atokenizer%2Fprimitives.dart","uri":"package:tokenizer/primitives.dart","_kind":"library"},"hits":[4,1,18,0,23,0,26,0,27,0,31,0,32,0,33,0,34,0,37,1,38,2,39,3,40,0,43,0,44,0,45,0,46,0,50,1,51,2,52,1,55,0,56,0,57,0,61,0,62,0,63,0,11,1]},{"source":"package:tokenizer/exceptions.dart","script":{"type":"@Script","fixedId":true,"id":"libraries/1/scripts/package%3Atokenizer%2Fexceptions.dart","uri":"package:tokenizer/exceptions.dart","_kind":"library"},"hits":[4,1]},{"source":"package:tokenizer/util.dart","script":{"type":"@Script","fixedId":true,"id":"libraries/1/scripts/package%3Atokenizer%2Futil.dart","uri":"package:tokenizer/util.dart","_kind":"library"},"hits":[4,1,5,3,8,1,11,0]}]}